NumpyChuxuezheZhinanZhongwenDisanbanChuyi/README.md
NumpyChuxuezheZhinanZhongwenDisanbanChuyi/__init__.py
NumpyChuxuezheZhinanZhongwenDisanbanChuyi/__main__.py
NumpyChuxuezheZhinanZhongwenDisanbanChuyi/file.epub
NumpyChuxuezheZhinanZhongwenDisanbanChuyi/index.html
NumpyChuxuezheZhinanZhongwenDisanbanChuyi/css/__init__.py
NumpyChuxuezheZhinanZhongwenDisanbanChuyi/css/annotations.css
NumpyChuxuezheZhinanZhongwenDisanbanChuyi/css/main.css
NumpyChuxuezheZhinanZhongwenDisanbanChuyi/css/normalize.css
NumpyChuxuezheZhinanZhongwenDisanbanChuyi/css/popup.css
NumpyChuxuezheZhinanZhongwenDisanbanChuyi/font/__init__.py
NumpyChuxuezheZhinanZhongwenDisanbanChuyi/font/fontello.eot
NumpyChuxuezheZhinanZhongwenDisanbanChuyi/font/fontello.svg
NumpyChuxuezheZhinanZhongwenDisanbanChuyi/font/fontello.ttf
NumpyChuxuezheZhinanZhongwenDisanbanChuyi/font/fontello.woff
NumpyChuxuezheZhinanZhongwenDisanbanChuyi/img/__init__.py
NumpyChuxuezheZhinanZhongwenDisanbanChuyi/img/annotator-glyph-sprite.png
NumpyChuxuezheZhinanZhongwenDisanbanChuyi/img/annotator-icon-sprite.png
NumpyChuxuezheZhinanZhongwenDisanbanChuyi/img/apple-touch-icon.png
NumpyChuxuezheZhinanZhongwenDisanbanChuyi/img/cancelfullscreen.png
NumpyChuxuezheZhinanZhongwenDisanbanChuyi/img/close.png
NumpyChuxuezheZhinanZhongwenDisanbanChuyi/img/fullscreen.png
NumpyChuxuezheZhinanZhongwenDisanbanChuyi/img/loader.gif
NumpyChuxuezheZhinanZhongwenDisanbanChuyi/img/menu-icon.png
NumpyChuxuezheZhinanZhongwenDisanbanChuyi/img/save.png
NumpyChuxuezheZhinanZhongwenDisanbanChuyi/img/saved.png
NumpyChuxuezheZhinanZhongwenDisanbanChuyi/img/settings-s.png
NumpyChuxuezheZhinanZhongwenDisanbanChuyi/img/settings.png
NumpyChuxuezheZhinanZhongwenDisanbanChuyi/img/star.png
NumpyChuxuezheZhinanZhongwenDisanbanChuyi/js/__init__.py
NumpyChuxuezheZhinanZhongwenDisanbanChuyi/js/epub.js
NumpyChuxuezheZhinanZhongwenDisanbanChuyi/js/epub.min.js
NumpyChuxuezheZhinanZhongwenDisanbanChuyi/js/epub.min.map
NumpyChuxuezheZhinanZhongwenDisanbanChuyi/js/hooks.min.js
numpy_chuxuezhe_zhinan_zhongwen_disanban_chuyi-2024.3.5.0.dist-info/METADATA
numpy_chuxuezhe_zhinan_zhongwen_disanban_chuyi-2024.3.5.0.dist-info/WHEEL
numpy_chuxuezhe_zhinan_zhongwen_disanban_chuyi-2024.3.5.0.dist-info/entry_points.txt
numpy_chuxuezhe_zhinan_zhongwen_disanban_chuyi-2024.3.5.0.dist-info/top_level.txt
numpy_chuxuezhe_zhinan_zhongwen_disanban_chuyi-2024.3.5.0.dist-info/RECORD
